ErisPulse_GitHubParser/Core.py
ErisPulse_GitHubParser/__init__.py
erispulse_githubparser-1.0.2.dist-info/licenses/LICENSE
erispulse_githubparser-1.0.2.dist-info/METADATA
erispulse_githubparser-1.0.2.dist-info/WHEEL
erispulse_githubparser-1.0.2.dist-info/entry_points.txt
erispulse_githubparser-1.0.2.dist-info/top_level.txt
erispulse_githubparser-1.0.2.dist-info/RECORD
