Metadata-Version: 2.4
Name: ErisPulse-GitHubParser
Version: 1.0.2
Summary: GitHub链接解析模块，自动解析仓库/Issue/PR信息并以最佳格式展示
Author-email: wsu2059q <wsu2059@qq.com>
License: MIT License
Project-URL: homepage, https://github.com/wsu2059q/ErisPulse-GitHubParser
Requires-Python: >=3.10
License-File: LICENSE
Dynamic: license-file
